ip_sibylsys/__init__.py
ip_sibylsys/adv_text.py
ip_sibylsys/ass_part.py
ip_sibylsys/events.py
ip_sibylsys/frame.py
ip_sibylsys/match.py
ip_sibylsys/read_ini.py
ip_sibylsys/styles.py
ip_sibylsys/time_fix.py
ip_sibylsys-0.1.0.dist-info/LICENSE
ip_sibylsys-0.1.0.dist-info/METADATA
ip_sibylsys-0.1.0.dist-info/WHEEL
ip_sibylsys-0.1.0.dist-info/top_level.txt
ip_sibylsys-0.1.0.dist-info/RECORD
